main.py
wayspiritmcp_enconly-0.1.3.dist-info/METADATA
wayspiritmcp_enconly-0.1.3.dist-info/WHEEL
wayspiritmcp_enconly-0.1.3.dist-info/entry_points.txt
wayspiritmcp_enconly-0.1.3.dist-info/top_level.txt
wayspiritmcp_enconly-0.1.3.dist-info/RECORD
